capture/__init__.py
capture/run.py
capture_run-0.1.0.dist-info/LICENSE
capture_run-0.1.0.dist-info/METADATA
capture_run-0.1.0.dist-info/WHEEL
capture_run-0.1.0.dist-info/RECORD
