Metadata-Version: 2.1
Name: capture-run
Version: 0.1.0
Summary: A drop-in replacement for `subprocess.run` that captures stdout and stderr while also displaying output live in the console.
License: MIT
Keywords: subprocess,run,popen,capture_output
Author: Christoph Dörrer
Author-email: d-chris@web.de
Requires-Python: >=3.8,<4.0
Classifier: License :: OSI Approved :: MIT License
Classifier: Operating System :: OS Independent
Classifier: Programming Language :: Python :: 3
Classifier: Programming Language :: Python :: 3.8
Classifier: Programming Language :: Python :: 3.9
Classifier: Programming Language :: Python :: 3.10
Classifier: Programming Language :: Python :: 3.11
Classifier: Programming Language :: Python :: 3.12
Classifier: Programming Language :: Python :: 3.13
Project-URL: repository, https://github.com/d-chris/capture-run
